{
  "##characteristics#compile#binary_size#all": [
    98584
  ], 
  "##characteristics#compile#binary_size#all_unique": [
    98584
  ], 
  "##characteristics#compile#binary_size#center": 98584, 
  "##characteristics#compile#binary_size#exp": 98584.0, 
  "##characteristics#compile#binary_size#exp_allx": [
    98584.0
  ], 
  "##characteristics#compile#binary_size#exp_ally": [
    100.0
  ], 
  "##characteristics#compile#binary_size#exp_warning": "no", 
  "##characteristics#compile#binary_size#halfrange": 0, 
  "##characteristics#compile#binary_size#max": 98584, 
  "##characteristics#compile#binary_size#mean": 98584.0, 
  "##characteristics#compile#binary_size#min": 98584, 
  "##characteristics#compile#binary_size#range": 0, 
  "##characteristics#compile#binary_size#range_percent": 0, 
  "##characteristics#compile#binary_size#repeats": 1, 
  "##characteristics#compile#compilation_success#all": [
    "yes"
  ], 
  "##characteristics#compile#compilation_success#all_unique": [
    "yes"
  ], 
  "##characteristics#compile#compilation_success#min": "yes", 
  "##characteristics#compile#compilation_success#repeats": 1, 
  "##characteristics#compile#compilation_success_bool#all": [
    true
  ], 
  "##characteristics#compile#compilation_success_bool#all_unique": [
    true
  ], 
  "##characteristics#compile#compilation_success_bool#min": true, 
  "##characteristics#compile#compilation_success_bool#repeats": 1, 
  "##characteristics#compile#compilation_time#all": [
    1.5828089714050293
  ], 
  "##characteristics#compile#compilation_time#all_unique": [
    1.5828089714050293
  ], 
  "##characteristics#compile#compilation_time#center": 1.5828089714050293, 
  "##characteristics#compile#compilation_time#exp": 1.5828089714050293, 
  "##characteristics#compile#compilation_time#exp_allx": [
    1.5828089714050293
  ], 
  "##characteristics#compile#compilation_time#exp_ally": [
    100.0
  ], 
  "##characteristics#compile#compilation_time#exp_warning": "no", 
  "##characteristics#compile#compilation_time#halfrange": 0.0, 
  "##characteristics#compile#compilation_time#max": 1.5828089714050293, 
  "##characteristics#compile#compilation_time#mean": 1.5828089714050293, 
  "##characteristics#compile#compilation_time#min": 1.5828089714050293, 
  "##characteristics#compile#compilation_time#range": 0.0, 
  "##characteristics#compile#compilation_time#range_percent": 0.0, 
  "##characteristics#compile#compilation_time#repeats": 1, 
  "##characteristics#compile#compilation_time_with_module#all": [
    2.6908180713653564
  ], 
  "##characteristics#compile#compilation_time_with_module#all_unique": [
    2.6908180713653564
  ], 
  "##characteristics#compile#compilation_time_with_module#center": 2.6908180713653564, 
  "##characteristics#compile#compilation_time_with_module#exp": 2.6908180713653564, 
  "##characteristics#compile#compilation_time_with_module#exp_allx": [
    2.6908180713653564
  ], 
  "##characteristics#compile#compilation_time_with_module#exp_ally": [
    100.0
  ], 
  "##characteristics#compile#compilation_time_with_module#exp_warning": "no", 
  "##characteristics#compile#compilation_time_with_module#halfrange": 0.0, 
  "##characteristics#compile#compilation_time_with_module#max": 2.6908180713653564, 
  "##characteristics#compile#compilation_time_with_module#mean": 2.6908180713653564, 
  "##characteristics#compile#compilation_time_with_module#min": 2.6908180713653564, 
  "##characteristics#compile#compilation_time_with_module#range": 0.0, 
  "##characteristics#compile#compilation_time_with_module#range_percent": 0.0, 
  "##characteristics#compile#compilation_time_with_module#repeats": 1, 
  "##characteristics#compile#joined_compiler_flags#all": [
    "-O3"
  ], 
  "##characteristics#compile#joined_compiler_flags#all_unique": [
    "-O3"
  ], 
  "##characteristics#compile#joined_compiler_flags#min": "-O3", 
  "##characteristics#compile#joined_compiler_flags#repeats": 1, 
  "##characteristics#compile#md5_sum#all": [
    "2f297103bd3d9189954b2e2480c4c0cd"
  ], 
  "##characteristics#compile#md5_sum#all_unique": [
    "2f297103bd3d9189954b2e2480c4c0cd"
  ], 
  "##characteristics#compile#md5_sum#min": "2f297103bd3d9189954b2e2480c4c0cd", 
  "##characteristics#compile#md5_sum#repeats": 1, 
  "##characteristics#compile#obj_size#all": [
    142168
  ], 
  "##characteristics#compile#obj_size#all_unique": [
    142168
  ], 
  "##characteristics#compile#obj_size#center": 142168, 
  "##characteristics#compile#obj_size#exp": 142168.0, 
  "##characteristics#compile#obj_size#exp_allx": [
    142168.0
  ], 
  "##characteristics#compile#obj_size#exp_ally": [
    100.0
  ], 
  "##characteristics#compile#obj_size#exp_warning": "no", 
  "##characteristics#compile#obj_size#halfrange": 0, 
  "##characteristics#compile#obj_size#max": 142168, 
  "##characteristics#compile#obj_size#mean": 142168.0, 
  "##characteristics#compile#obj_size#min": 142168, 
  "##characteristics#compile#obj_size#range": 0, 
  "##characteristics#compile#obj_size#range_percent": 0, 
  "##characteristics#compile#obj_size#repeats": 1, 
  "##characteristics#compile#obj_sizes#add.o#all": [
    5088
  ], 
  "##characteristics#compile#obj_sizes#add.o#all_unique": [
    5088
  ], 
  "##characteristics#compile#obj_sizes#add.o#center": 5088, 
  "##characteristics#compile#obj_sizes#add.o#exp": 5088.0, 
  "##characteristics#compile#obj_sizes#add.o#exp_allx": [
    5088.0
  ], 
  "##characteristics#compile#obj_sizes#add.o#exp_ally": [
    100.0
  ], 
  "##characteristics#compile#obj_sizes#add.o#exp_warning": "no", 
  "##characteristics#compile#obj_sizes#add.o#halfrange": 0, 
  "##characteristics#compile#obj_sizes#add.o#max": 5088, 
  "##characteristics#compile#obj_sizes#add.o#mean": 5088.0, 
  "##characteristics#compile#obj_sizes#add.o#min": 5088, 
  "##characteristics#compile#obj_sizes#add.o#range": 0, 
  "##characteristics#compile#obj_sizes#add.o#range_percent": 0, 
  "##characteristics#compile#obj_sizes#add.o#repeats": 1, 
  "##characteristics#compile#obj_sizes#code.o#all": [
    2480
  ], 
  "##characteristics#compile#obj_sizes#code.o#all_unique": [
    2480
  ], 
  "##characteristics#compile#obj_sizes#code.o#center": 2480, 
  "##characteristics#compile#obj_sizes#code.o#exp": 2480.0, 
  "##characteristics#compile#obj_sizes#code.o#exp_allx": [
    2480.0
  ], 
  "##characteristics#compile#obj_sizes#code.o#exp_ally": [
    100.0
  ], 
  "##characteristics#compile#obj_sizes#code.o#exp_warning": "no", 
  "##characteristics#compile#obj_sizes#code.o#halfrange": 0, 
  "##characteristics#compile#obj_sizes#code.o#max": 2480, 
  "##characteristics#compile#obj_sizes#code.o#mean": 2480.0, 
  "##characteristics#compile#obj_sizes#code.o#min": 2480, 
  "##characteristics#compile#obj_sizes#code.o#range": 0, 
  "##characteristics#compile#obj_sizes#code.o#range_percent": 0, 
  "##characteristics#compile#obj_sizes#code.o#repeats": 1, 
  "##characteristics#compile#obj_sizes#ctuning-rtl.o#all": [
    2440
  ], 
  "##characteristics#compile#obj_sizes#ctuning-rtl.o#all_unique": [
    2440
  ], 
  "##characteristics#compile#obj_sizes#ctuning-rtl.o#center": 2440, 
  "##characteristics#compile#obj_sizes#ctuning-rtl.o#exp": 2440.0, 
  "##characteristics#compile#obj_sizes#ctuning-rtl.o#exp_allx": [
    2440.0
  ], 
  "##characteristics#compile#obj_sizes#ctuning-rtl.o#exp_ally": [
    100.0
  ], 
  "##characteristics#compile#obj_sizes#ctuning-rtl.o#exp_warning": "no", 
  "##characteristics#compile#obj_sizes#ctuning-rtl.o#halfrange": 0, 
  "##characteristics#compile#obj_sizes#ctuning-rtl.o#max": 2440, 
  "##characteristics#compile#obj_sizes#ctuning-rtl.o#mean": 2440.0, 
  "##characteristics#compile#obj_sizes#ctuning-rtl.o#min": 2440, 
  "##characteristics#compile#obj_sizes#ctuning-rtl.o#range": 0, 
  "##characteristics#compile#obj_sizes#ctuning-rtl.o#range_percent": 0, 
  "##characteristics#compile#obj_sizes#ctuning-rtl.o#repeats": 1, 
  "##characteristics#compile#obj_sizes#debug.o#all": [
    3032
  ], 
  "##characteristics#compile#obj_sizes#debug.o#all_unique": [
    3032
  ], 
  "##characteristics#compile#obj_sizes#debug.o#center": 3032, 
  "##characteristics#compile#obj_sizes#debug.o#exp": 3032.0, 
  "##characteristics#compile#obj_sizes#debug.o#exp_allx": [
    3032.0
  ], 
  "##characteristics#compile#obj_sizes#debug.o#exp_ally": [
    100.0
  ], 
  "##characteristics#compile#obj_sizes#debug.o#exp_warning": "no", 
  "##characteristics#compile#obj_sizes#debug.o#halfrange": 0, 
  "##characteristics#compile#obj_sizes#debug.o#max": 3032, 
  "##characteristics#compile#obj_sizes#debug.o#mean": 3032.0, 
  "##characteristics#compile#obj_sizes#debug.o#min": 3032, 
  "##characteristics#compile#obj_sizes#debug.o#range": 0, 
  "##characteristics#compile#obj_sizes#debug.o#range_percent": 0, 
  "##characteristics#compile#obj_sizes#debug.o#repeats": 1, 
  "##characteristics#compile#obj_sizes#decode.o#all": [
    2280
  ], 
  "##characteristics#compile#obj_sizes#decode.o#all_unique": [
    2280
  ], 
  "##characteristics#compile#obj_sizes#decode.o#center": 2280, 
  "##characteristics#compile#obj_sizes#decode.o#exp": 2280.0, 
  "##characteristics#compile#obj_sizes#decode.o#exp_allx": [
    2280.0
  ], 
  "##characteristics#compile#obj_sizes#decode.o#exp_ally": [
    100.0
  ], 
  "##characteristics#compile#obj_sizes#decode.o#exp_warning": "no", 
  "##characteristics#compile#obj_sizes#decode.o#halfrange": 0, 
  "##characteristics#compile#obj_sizes#decode.o#max": 2280, 
  "##characteristics#compile#obj_sizes#decode.o#mean": 2280.0, 
  "##characteristics#compile#obj_sizes#decode.o#min": 2280, 
  "##characteristics#compile#obj_sizes#decode.o#range": 0, 
  "##characteristics#compile#obj_sizes#decode.o#range_percent": 0, 
  "##characteristics#compile#obj_sizes#decode.o#repeats": 1, 
  "##characteristics#compile#obj_sizes#getopt.o#all": [
    936
  ], 
  "##characteristics#compile#obj_sizes#getopt.o#all_unique": [
    936
  ], 
  "##characteristics#compile#obj_sizes#getopt.o#center": 936, 
  "##characteristics#compile#obj_sizes#getopt.o#exp": 936.0, 
  "##characteristics#compile#obj_sizes#getopt.o#exp_allx": [
    936.0
  ], 
  "##characteristics#compile#obj_sizes#getopt.o#exp_ally": [
    100.0
  ], 
  "##characteristics#compile#obj_sizes#getopt.o#exp_warning": "no", 
  "##characteristics#compile#obj_sizes#getopt.o#halfrange": 0, 
  "##characteristics#compile#obj_sizes#getopt.o#max": 936, 
  "##characteristics#compile#obj_sizes#getopt.o#mean": 936.0, 
  "##characteristics#compile#obj_sizes#getopt.o#min": 936, 
  "##characteristics#compile#obj_sizes#getopt.o#range": 0, 
  "##characteristics#compile#obj_sizes#getopt.o#range_percent": 0, 
  "##characteristics#compile#obj_sizes#getopt.o#repeats": 1, 
  "##characteristics#compile#obj_sizes#gsm_create.o#all": [
    1488
  ], 
  "##characteristics#compile#obj_sizes#gsm_create.o#all_unique": [
    1488
  ], 
  "##characteristics#compile#obj_sizes#gsm_create.o#center": 1488, 
  "##characteristics#compile#obj_sizes#gsm_create.o#exp": 1488.0, 
  "##characteristics#compile#obj_sizes#gsm_create.o#exp_allx": [
    1488.0
  ], 
  "##characteristics#compile#obj_sizes#gsm_create.o#exp_ally": [
    100.0
  ], 
  "##characteristics#compile#obj_sizes#gsm_create.o#exp_warning": "no", 
  "##characteristics#compile#obj_sizes#gsm_create.o#halfrange": 0, 
  "##characteristics#compile#obj_sizes#gsm_create.o#max": 1488, 
  "##characteristics#compile#obj_sizes#gsm_create.o#mean": 1488.0, 
  "##characteristics#compile#obj_sizes#gsm_create.o#min": 1488, 
  "##characteristics#compile#obj_sizes#gsm_create.o#range": 0, 
  "##characteristics#compile#obj_sizes#gsm_create.o#range_percent": 0, 
  "##characteristics#compile#obj_sizes#gsm_create.o#repeats": 1, 
  "##characteristics#compile#obj_sizes#gsm_decode.o#all": [
    3096
  ], 
  "##characteristics#compile#obj_sizes#gsm_decode.o#all_unique": [
    3096
  ], 
  "##characteristics#compile#obj_sizes#gsm_decode.o#center": 3096, 
  "##characteristics#compile#obj_sizes#gsm_decode.o#exp": 3096.0, 
  "##characteristics#compile#obj_sizes#gsm_decode.o#exp_allx": [
    3096.0
  ], 
  "##characteristics#compile#obj_sizes#gsm_decode.o#exp_ally": [
    100.0
  ], 
  "##characteristics#compile#obj_sizes#gsm_decode.o#exp_warning": "no", 
  "##characteristics#compile#obj_sizes#gsm_decode.o#halfrange": 0, 
  "##characteristics#compile#obj_sizes#gsm_decode.o#max": 3096, 
  "##characteristics#compile#obj_sizes#gsm_decode.o#mean": 3096.0, 
  "##characteristics#compile#obj_sizes#gsm_decode.o#min": 3096, 
  "##characteristics#compile#obj_sizes#gsm_decode.o#range": 0, 
  "##characteristics#compile#obj_sizes#gsm_decode.o#range_percent": 0, 
  "##characteristics#compile#obj_sizes#gsm_decode.o#repeats": 1, 
  "##characteristics#compile#obj_sizes#gsm_destroy.o#all": [
    1464
  ], 
  "##characteristics#compile#obj_sizes#gsm_destroy.o#all_unique": [
    1464
  ], 
  "##characteristics#compile#obj_sizes#gsm_destroy.o#center": 1464, 
  "##characteristics#compile#obj_sizes#gsm_destroy.o#exp": 1464.0, 
  "##characteristics#compile#obj_sizes#gsm_destroy.o#exp_allx": [
    1464.0
  ], 
  "##characteristics#compile#obj_sizes#gsm_destroy.o#exp_ally": [
    100.0
  ], 
  "##characteristics#compile#obj_sizes#gsm_destroy.o#exp_warning": "no", 
  "##characteristics#compile#obj_sizes#gsm_destroy.o#halfrange": 0, 
  "##characteristics#compile#obj_sizes#gsm_destroy.o#max": 1464, 
  "##characteristics#compile#obj_sizes#gsm_destroy.o#mean": 1464.0, 
  "##characteristics#compile#obj_sizes#gsm_destroy.o#min": 1464, 
  "##characteristics#compile#obj_sizes#gsm_destroy.o#range": 0, 
  "##characteristics#compile#obj_sizes#gsm_destroy.o#range_percent": 0, 
  "##characteristics#compile#obj_sizes#gsm_destroy.o#repeats": 1, 
  "##characteristics#compile#obj_sizes#gsm_encode.o#all": [
    2896
  ], 
  "##characteristics#compile#obj_sizes#gsm_encode.o#all_unique": [
    2896
  ], 
  "##characteristics#compile#obj_sizes#gsm_encode.o#center": 2896, 
  "##characteristics#compile#obj_sizes#gsm_encode.o#exp": 2896.0, 
  "##characteristics#compile#obj_sizes#gsm_encode.o#exp_allx": [
    2896.0
  ], 
  "##characteristics#compile#obj_sizes#gsm_encode.o#exp_ally": [
    100.0
  ], 
  "##characteristics#compile#obj_sizes#gsm_encode.o#exp_warning": "no", 
  "##characteristics#compile#obj_sizes#gsm_encode.o#halfrange": 0, 
  "##characteristics#compile#obj_sizes#gsm_encode.o#max": 2896, 
  "##characteristics#compile#obj_sizes#gsm_encode.o#mean": 2896.0, 
  "##characteristics#compile#obj_sizes#gsm_encode.o#min": 2896, 
  "##characteristics#compile#obj_sizes#gsm_encode.o#range": 0, 
  "##characteristics#compile#obj_sizes#gsm_encode.o#range_percent": 0, 
  "##characteristics#compile#obj_sizes#gsm_encode.o#repeats": 1, 
  "##characteristics#compile#obj_sizes#gsm_explode.o#all": [
    2776
  ], 
  "##characteristics#compile#obj_sizes#gsm_explode.o#all_unique": [
    2776
  ], 
  "##characteristics#compile#obj_sizes#gsm_explode.o#center": 2776, 
  "##characteristics#compile#obj_sizes#gsm_explode.o#exp": 2776.0, 
  "##characteristics#compile#obj_sizes#gsm_explode.o#exp_allx": [
    2776.0
  ], 
  "##characteristics#compile#obj_sizes#gsm_explode.o#exp_ally": [
    100.0
  ], 
  "##characteristics#compile#obj_sizes#gsm_explode.o#exp_warning": "no", 
  "##characteristics#compile#obj_sizes#gsm_explode.o#halfrange": 0, 
  "##characteristics#compile#obj_sizes#gsm_explode.o#max": 2776, 
  "##characteristics#compile#obj_sizes#gsm_explode.o#mean": 2776.0, 
  "##characteristics#compile#obj_sizes#gsm_explode.o#min": 2776, 
  "##characteristics#compile#obj_sizes#gsm_explode.o#range": 0, 
  "##characteristics#compile#obj_sizes#gsm_explode.o#range_percent": 0, 
  "##characteristics#compile#obj_sizes#gsm_explode.o#repeats": 1, 
  "##characteristics#compile#obj_sizes#gsm_implode.o#all": [
    2504
  ], 
  "##characteristics#compile#obj_sizes#gsm_implode.o#all_unique": [
    2504
  ], 
  "##characteristics#compile#obj_sizes#gsm_implode.o#center": 2504, 
  "##characteristics#compile#obj_sizes#gsm_implode.o#exp": 2504.0, 
  "##characteristics#compile#obj_sizes#gsm_implode.o#exp_allx": [
    2504.0
  ], 
  "##characteristics#compile#obj_sizes#gsm_implode.o#exp_ally": [
    100.0
  ], 
  "##characteristics#compile#obj_sizes#gsm_implode.o#exp_warning": "no", 
  "##characteristics#compile#obj_sizes#gsm_implode.o#halfrange": 0, 
  "##characteristics#compile#obj_sizes#gsm_implode.o#max": 2504, 
  "##characteristics#compile#obj_sizes#gsm_implode.o#mean": 2504.0, 
  "##characteristics#compile#obj_sizes#gsm_implode.o#min": 2504, 
  "##characteristics#compile#obj_sizes#gsm_implode.o#range": 0, 
  "##characteristics#compile#obj_sizes#gsm_implode.o#range_percent": 0, 
  "##characteristics#compile#obj_sizes#gsm_implode.o#repeats": 1, 
  "##characteristics#compile#obj_sizes#gsm_option.o#all": [
    1368
  ], 
  "##characteristics#compile#obj_sizes#gsm_option.o#all_unique": [
    1368
  ], 
  "##characteristics#compile#obj_sizes#gsm_option.o#center": 1368, 
  "##characteristics#compile#obj_sizes#gsm_option.o#exp": 1368.0, 
  "##characteristics#compile#obj_sizes#gsm_option.o#exp_allx": [
    1368.0
  ], 
  "##characteristics#compile#obj_sizes#gsm_option.o#exp_ally": [
    100.0
  ], 
  "##characteristics#compile#obj_sizes#gsm_option.o#exp_warning": "no", 
  "##characteristics#compile#obj_sizes#gsm_option.o#halfrange": 0, 
  "##characteristics#compile#obj_sizes#gsm_option.o#max": 1368, 
  "##characteristics#compile#obj_sizes#gsm_option.o#mean": 1368.0, 
  "##characteristics#compile#obj_sizes#gsm_option.o#min": 1368, 
  "##characteristics#compile#obj_sizes#gsm_option.o#range": 0, 
  "##characteristics#compile#obj_sizes#gsm_option.o#range_percent": 0, 
  "##characteristics#compile#obj_sizes#gsm_option.o#repeats": 1, 
  "##characteristics#compile#obj_sizes#gsm_print.o#all": [
    4240
  ], 
  "##characteristics#compile#obj_sizes#gsm_print.o#all_unique": [
    4240
  ], 
  "##characteristics#compile#obj_sizes#gsm_print.o#center": 4240, 
  "##characteristics#compile#obj_sizes#gsm_print.o#exp": 4240.0, 
  "##characteristics#compile#obj_sizes#gsm_print.o#exp_allx": [
    4240.0
  ], 
  "##characteristics#compile#obj_sizes#gsm_print.o#exp_ally": [
    100.0
  ], 
  "##characteristics#compile#obj_sizes#gsm_print.o#exp_warning": "no", 
  "##characteristics#compile#obj_sizes#gsm_print.o#halfrange": 0, 
  "##characteristics#compile#obj_sizes#gsm_print.o#max": 4240, 
  "##characteristics#compile#obj_sizes#gsm_print.o#mean": 4240.0, 
  "##characteristics#compile#obj_sizes#gsm_print.o#min": 4240, 
  "##characteristics#compile#obj_sizes#gsm_print.o#range": 0, 
  "##characteristics#compile#obj_sizes#gsm_print.o#range_percent": 0, 
  "##characteristics#compile#obj_sizes#gsm_print.o#repeats": 1, 
  "##characteristics#compile#obj_sizes#long_term.o#all": [
    9016
  ], 
  "##characteristics#compile#obj_sizes#long_term.o#all_unique": [
    9016
  ], 
  "##characteristics#compile#obj_sizes#long_term.o#center": 9016, 
  "##characteristics#compile#obj_sizes#long_term.o#exp": 9016.0, 
  "##characteristics#compile#obj_sizes#long_term.o#exp_allx": [
    9016.0
  ], 
  "##characteristics#compile#obj_sizes#long_term.o#exp_ally": [
    100.0
  ], 
  "##characteristics#compile#obj_sizes#long_term.o#exp_warning": "no", 
  "##characteristics#compile#obj_sizes#long_term.o#halfrange": 0, 
  "##characteristics#compile#obj_sizes#long_term.o#max": 9016, 
  "##characteristics#compile#obj_sizes#long_term.o#mean": 9016.0, 
  "##characteristics#compile#obj_sizes#long_term.o#min": 9016, 
  "##characteristics#compile#obj_sizes#long_term.o#range": 0, 
  "##characteristics#compile#obj_sizes#long_term.o#range_percent": 0, 
  "##characteristics#compile#obj_sizes#long_term.o#repeats": 1, 
  "##characteristics#compile#obj_sizes#lpc.o#all": [
    11552
  ], 
  "##characteristics#compile#obj_sizes#lpc.o#all_unique": [
    11552
  ], 
  "##characteristics#compile#obj_sizes#lpc.o#center": 11552, 
  "##characteristics#compile#obj_sizes#lpc.o#exp": 11552.0, 
  "##characteristics#compile#obj_sizes#lpc.o#exp_allx": [
    11552.0
  ], 
  "##characteristics#compile#obj_sizes#lpc.o#exp_ally": [
    100.0
  ], 
  "##characteristics#compile#obj_sizes#lpc.o#exp_warning": "no", 
  "##characteristics#compile#obj_sizes#lpc.o#halfrange": 0, 
  "##characteristics#compile#obj_sizes#lpc.o#max": 11552, 
  "##characteristics#compile#obj_sizes#lpc.o#mean": 11552.0, 
  "##characteristics#compile#obj_sizes#lpc.o#min": 11552, 
  "##characteristics#compile#obj_sizes#lpc.o#range": 0, 
  "##characteristics#compile#obj_sizes#lpc.o#range_percent": 0, 
  "##characteristics#compile#obj_sizes#lpc.o#repeats": 1, 
  "##characteristics#compile#obj_sizes#preprocess.o#all": [
    2296
  ], 
  "##characteristics#compile#obj_sizes#preprocess.o#all_unique": [
    2296
  ], 
  "##characteristics#compile#obj_sizes#preprocess.o#center": 2296, 
  "##characteristics#compile#obj_sizes#preprocess.o#exp": 2296.0, 
  "##characteristics#compile#obj_sizes#preprocess.o#exp_allx": [
    2296.0
  ], 
  "##characteristics#compile#obj_sizes#preprocess.o#exp_ally": [
    100.0
  ], 
  "##characteristics#compile#obj_sizes#preprocess.o#exp_warning": "no", 
  "##characteristics#compile#obj_sizes#preprocess.o#halfrange": 0, 
  "##characteristics#compile#obj_sizes#preprocess.o#max": 2296, 
  "##characteristics#compile#obj_sizes#preprocess.o#mean": 2296.0, 
  "##characteristics#compile#obj_sizes#preprocess.o#min": 2296, 
  "##characteristics#compile#obj_sizes#preprocess.o#range": 0, 
  "##characteristics#compile#obj_sizes#preprocess.o#range_percent": 0, 
  "##characteristics#compile#obj_sizes#preprocess.o#repeats": 1, 
  "##characteristics#compile#obj_sizes#rpe.o#all": [
    8640
  ], 
  "##characteristics#compile#obj_sizes#rpe.o#all_unique": [
    8640
  ], 
  "##characteristics#compile#obj_sizes#rpe.o#center": 8640, 
  "##characteristics#compile#obj_sizes#rpe.o#exp": 8640.0, 
  "##characteristics#compile#obj_sizes#rpe.o#exp_allx": [
    8640.0
  ], 
  "##characteristics#compile#obj_sizes#rpe.o#exp_ally": [
    100.0
  ], 
  "##characteristics#compile#obj_sizes#rpe.o#exp_warning": "no", 
  "##characteristics#compile#obj_sizes#rpe.o#halfrange": 0, 
  "##characteristics#compile#obj_sizes#rpe.o#max": 8640, 
  "##characteristics#compile#obj_sizes#rpe.o#mean": 8640.0, 
  "##characteristics#compile#obj_sizes#rpe.o#min": 8640, 
  "##characteristics#compile#obj_sizes#rpe.o#range": 0, 
  "##characteristics#compile#obj_sizes#rpe.o#range_percent": 0, 
  "##characteristics#compile#obj_sizes#rpe.o#repeats": 1, 
  "##characteristics#compile#obj_sizes#short_term.o#all": [
    22192
  ], 
  "##characteristics#compile#obj_sizes#short_term.o#all_unique": [
    22192
  ], 
  "##characteristics#compile#obj_sizes#short_term.o#center": 22192, 
  "##characteristics#compile#obj_sizes#short_term.o#exp": 22192.0, 
  "##characteristics#compile#obj_sizes#short_term.o#exp_allx": [
    22192.0
  ], 
  "##characteristics#compile#obj_sizes#short_term.o#exp_ally": [
    100.0
  ], 
  "##characteristics#compile#obj_sizes#short_term.o#exp_warning": "no", 
  "##characteristics#compile#obj_sizes#short_term.o#halfrange": 0, 
  "##characteristics#compile#obj_sizes#short_term.o#max": 22192, 
  "##characteristics#compile#obj_sizes#short_term.o#mean": 22192.0, 
  "##characteristics#compile#obj_sizes#short_term.o#min": 22192, 
  "##characteristics#compile#obj_sizes#short_term.o#range": 0, 
  "##characteristics#compile#obj_sizes#short_term.o#range_percent": 0, 
  "##characteristics#compile#obj_sizes#short_term.o#repeats": 1, 
  "##characteristics#compile#obj_sizes#table.o#all": [
    1416
  ], 
  "##characteristics#compile#obj_sizes#table.o#all_unique": [
    1416
  ], 
  "##characteristics#compile#obj_sizes#table.o#center": 1416, 
  "##characteristics#compile#obj_sizes#table.o#exp": 1416.0, 
  "##characteristics#compile#obj_sizes#table.o#exp_allx": [
    1416.0
  ], 
  "##characteristics#compile#obj_sizes#table.o#exp_ally": [
    100.0
  ], 
  "##characteristics#compile#obj_sizes#table.o#exp_warning": "no", 
  "##characteristics#compile#obj_sizes#table.o#halfrange": 0, 
  "##characteristics#compile#obj_sizes#table.o#max": 1416, 
  "##characteristics#compile#obj_sizes#table.o#mean": 1416.0, 
  "##characteristics#compile#obj_sizes#table.o#min": 1416, 
  "##characteristics#compile#obj_sizes#table.o#range": 0, 
  "##characteristics#compile#obj_sizes#table.o#range_percent": 0, 
  "##characteristics#compile#obj_sizes#table.o#repeats": 1, 
  "##characteristics#compile#obj_sizes#toast.o#all": [
    25848
  ], 
  "##characteristics#compile#obj_sizes#toast.o#all_unique": [
    25848
  ], 
  "##characteristics#compile#obj_sizes#toast.o#center": 25848, 
  "##characteristics#compile#obj_sizes#toast.o#exp": 25848.0, 
  "##characteristics#compile#obj_sizes#toast.o#exp_allx": [
    25848.0
  ], 
  "##characteristics#compile#obj_sizes#toast.o#exp_ally": [
    100.0
  ], 
  "##characteristics#compile#obj_sizes#toast.o#exp_warning": "no", 
  "##characteristics#compile#obj_sizes#toast.o#halfrange": 0, 
  "##characteristics#compile#obj_sizes#toast.o#max": 25848, 
  "##characteristics#compile#obj_sizes#toast.o#mean": 25848.0, 
  "##characteristics#compile#obj_sizes#toast.o#min": 25848, 
  "##characteristics#compile#obj_sizes#toast.o#range": 0, 
  "##characteristics#compile#obj_sizes#toast.o#range_percent": 0, 
  "##characteristics#compile#obj_sizes#toast.o#repeats": 1, 
  "##characteristics#compile#obj_sizes#toast_alaw.o#all": [
    6856
  ], 
  "##characteristics#compile#obj_sizes#toast_alaw.o#all_unique": [
    6856
  ], 
  "##characteristics#compile#obj_sizes#toast_alaw.o#center": 6856, 
  "##characteristics#compile#obj_sizes#toast_alaw.o#exp": 6856.0, 
  "##characteristics#compile#obj_sizes#toast_alaw.o#exp_allx": [
    6856.0
  ], 
  "##characteristics#compile#obj_sizes#toast_alaw.o#exp_ally": [
    100.0
  ], 
  "##characteristics#compile#obj_sizes#toast_alaw.o#exp_warning": "no", 
  "##characteristics#compile#obj_sizes#toast_alaw.o#halfrange": 0, 
  "##characteristics#compile#obj_sizes#toast_alaw.o#max": 6856, 
  "##characteristics#compile#obj_sizes#toast_alaw.o#mean": 6856.0, 
  "##characteristics#compile#obj_sizes#toast_alaw.o#min": 6856, 
  "##characteristics#compile#obj_sizes#toast_alaw.o#range": 0, 
  "##characteristics#compile#obj_sizes#toast_alaw.o#range_percent": 0, 
  "##characteristics#compile#obj_sizes#toast_alaw.o#repeats": 1, 
  "##characteristics#compile#obj_sizes#toast_audio.o#all": [
    5544
  ], 
  "##characteristics#compile#obj_sizes#toast_audio.o#all_unique": [
    5544
  ], 
  "##characteristics#compile#obj_sizes#toast_audio.o#center": 5544, 
  "##characteristics#compile#obj_sizes#toast_audio.o#exp": 5544.0, 
  "##characteristics#compile#obj_sizes#toast_audio.o#exp_allx": [
    5544.0
  ], 
  "##characteristics#compile#obj_sizes#toast_audio.o#exp_ally": [
    100.0
  ], 
  "##characteristics#compile#obj_sizes#toast_audio.o#exp_warning": "no", 
  "##characteristics#compile#obj_sizes#toast_audio.o#halfrange": 0, 
  "##characteristics#compile#obj_sizes#toast_audio.o#max": 5544, 
  "##characteristics#compile#obj_sizes#toast_audio.o#mean": 5544.0, 
  "##characteristics#compile#obj_sizes#toast_audio.o#min": 5544, 
  "##characteristics#compile#obj_sizes#toast_audio.o#range": 0, 
  "##characteristics#compile#obj_sizes#toast_audio.o#range_percent": 0, 
  "##characteristics#compile#obj_sizes#toast_audio.o#repeats": 1, 
  "##characteristics#compile#obj_sizes#toast_lin.o#all": [
    1768
  ], 
  "##characteristics#compile#obj_sizes#toast_lin.o#all_unique": [
    1768
  ], 
  "##characteristics#compile#obj_sizes#toast_lin.o#center": 1768, 
  "##characteristics#compile#obj_sizes#toast_lin.o#exp": 1768.0, 
  "##characteristics#compile#obj_sizes#toast_lin.o#exp_allx": [
    1768.0
  ], 
  "##characteristics#compile#obj_sizes#toast_lin.o#exp_ally": [
    100.0
  ], 
  "##characteristics#compile#obj_sizes#toast_lin.o#exp_warning": "no", 
  "##characteristics#compile#obj_sizes#toast_lin.o#halfrange": 0, 
  "##characteristics#compile#obj_sizes#toast_lin.o#max": 1768, 
  "##characteristics#compile#obj_sizes#toast_lin.o#mean": 1768.0, 
  "##characteristics#compile#obj_sizes#toast_lin.o#min": 1768, 
  "##characteristics#compile#obj_sizes#toast_lin.o#range": 0, 
  "##characteristics#compile#obj_sizes#toast_lin.o#range_percent": 0, 
  "##characteristics#compile#obj_sizes#toast_lin.o#repeats": 1, 
  "##characteristics#compile#obj_sizes#toast_ulaw.o#all": [
    10952
  ], 
  "##characteristics#compile#obj_sizes#toast_ulaw.o#all_unique": [
    10952
  ], 
  "##characteristics#compile#obj_sizes#toast_ulaw.o#center": 10952, 
  "##characteristics#compile#obj_sizes#toast_ulaw.o#exp": 10952.0, 
  "##characteristics#compile#obj_sizes#toast_ulaw.o#exp_allx": [
    10952.0
  ], 
  "##characteristics#compile#obj_sizes#toast_ulaw.o#exp_ally": [
    100.0
  ], 
  "##characteristics#compile#obj_sizes#toast_ulaw.o#exp_warning": "no", 
  "##characteristics#compile#obj_sizes#toast_ulaw.o#halfrange": 0, 
  "##characteristics#compile#obj_sizes#toast_ulaw.o#max": 10952, 
  "##characteristics#compile#obj_sizes#toast_ulaw.o#mean": 10952.0, 
  "##characteristics#compile#obj_sizes#toast_ulaw.o#min": 10952, 
  "##characteristics#compile#obj_sizes#toast_ulaw.o#range": 0, 
  "##characteristics#compile#obj_sizes#toast_ulaw.o#range_percent": 0, 
  "##characteristics#compile#obj_sizes#toast_ulaw.o#repeats": 1, 
  "##characteristics#compile#program_git_hash#all": [
    "935232b0a32c97cba6e9f4ccde34c92e859a64df"
  ], 
  "##characteristics#compile#program_git_hash#all_unique": [
    "935232b0a32c97cba6e9f4ccde34c92e859a64df"
  ], 
  "##characteristics#compile#program_git_hash#min": "935232b0a32c97cba6e9f4ccde34c92e859a64df", 
  "##characteristics#compile#program_git_hash#repeats": 1, 
  "##characteristics#run#execution_time#all": [
    0.006940394419306184, 
    0.006931647058823529, 
    0.006918114630467572, 
    0.006924947963800904
  ], 
  "##characteristics#run#execution_time#all_unique": [
    0.006940394419306184, 
    0.006931647058823529, 
    0.006918114630467572, 
    0.006924947963800904
  ], 
  "##characteristics#run#execution_time#center": 0.006929254524886878, 
  "##characteristics#run#execution_time#exp": 0.0069268915169797525, 
  "##characteristics#run#execution_time#exp_allx": [
    0.0069268915169797525
  ], 
  "##characteristics#run#execution_time#exp_ally": [
    148.70402571832653
  ], 
  "##characteristics#run#execution_time#exp_warning": "no", 
  "##characteristics#run#execution_time#halfrange": 1.1139894419306268e-05, 
  "##characteristics#run#execution_time#max": 0.006940394419306184, 
  "##characteristics#run#execution_time#mean": 0.006928776018099548, 
  "##characteristics#run#execution_time#min": 0.006918114630467572, 
  "##characteristics#run#execution_time#range": 2.2279788838612535e-05, 
  "##characteristics#run#execution_time#range_percent": 0.0032205000970194565, 
  "##characteristics#run#execution_time#repeats": 4, 
  "##characteristics#run#execution_time_kernel_0#all": [
    9.202963, 
    9.191364, 
    9.17342, 
    9.182481
  ], 
  "##characteristics#run#execution_time_kernel_0#all_unique": [
    9.202963, 
    9.191364, 
    9.17342, 
    9.182481
  ], 
  "##characteristics#run#execution_time_kernel_0#center": 9.1881915, 
  "##characteristics#run#execution_time_kernel_0#exp": 9.185058151515152, 
  "##characteristics#run#execution_time_kernel_0#exp_allx": [
    9.185058151515152
  ], 
  "##characteristics#run#execution_time_kernel_0#exp_ally": [
    0.1121448157755102
  ], 
  "##characteristics#run#execution_time_kernel_0#exp_warning": "no", 
  "##characteristics#run#execution_time_kernel_0#halfrange": 0.01477150000000016, 
  "##characteristics#run#execution_time_kernel_0#max": 9.202963, 
  "##characteristics#run#execution_time_kernel_0#mean": 9.187557, 
  "##characteristics#run#execution_time_kernel_0#min": 9.17342, 
  "##characteristics#run#execution_time_kernel_0#range": 0.02954300000000032, 
  "##characteristics#run#execution_time_kernel_0#range_percent": 0.003220500097019467, 
  "##characteristics#run#execution_time_kernel_0#repeats": 4, 
  "##characteristics#run#execution_time_with_module#all": [
    9.711988925933838, 
    9.704675912857056, 
    9.68427300453186, 
    9.695204019546509
  ], 
  "##characteristics#run#execution_time_with_module#all_unique": [
    9.711988925933838, 
    9.704675912857056, 
    9.68427300453186, 
    9.695204019546509
  ], 
  "##characteristics#run#execution_time_with_module#center": 9.69813096523285, 
  "##characteristics#run#execution_time_with_module#exp": 9.696311233019587, 
  "##characteristics#run#execution_time_with_module#exp_allx": [
    9.696311233019587
  ], 
  "##characteristics#run#execution_time_with_module#exp_ally": [
    0.10623111443779065
  ], 
  "##characteristics#run#execution_time_with_module#exp_warning": "no", 
  "##characteristics#run#execution_time_with_module#halfrange": 0.01385796070098877, 
  "##characteristics#run#execution_time_with_module#max": 9.711988925933838, 
  "##characteristics#run#execution_time_with_module#mean": 9.699035465717316, 
  "##characteristics#run#execution_time_with_module#min": 9.68427300453186, 
  "##characteristics#run#execution_time_with_module#range": 0.02771592140197754, 
  "##characteristics#run#execution_time_with_module#range_percent": 0.002861951680730972, 
  "##characteristics#run#execution_time_with_module#repeats": 4, 
  "##characteristics#run#repeat#all": [
    1326, 
    1326, 
    1326, 
    1326
  ], 
  "##characteristics#run#repeat#all_unique": [
    1326
  ], 
  "##characteristics#run#repeat#center": 1326, 
  "##characteristics#run#repeat#exp": 1326.0, 
  "##characteristics#run#repeat#exp_allx": [
    1326.0
  ], 
  "##characteristics#run#repeat#exp_ally": [
    100.0
  ], 
  "##characteristics#run#repeat#exp_warning": "no", 
  "##characteristics#run#repeat#halfrange": 0, 
  "##characteristics#run#repeat#max": 1326, 
  "##characteristics#run#repeat#mean": 1326.0, 
  "##characteristics#run#repeat#min": 1326, 
  "##characteristics#run#repeat#range": 0, 
  "##characteristics#run#repeat#range_percent": 0, 
  "##characteristics#run#repeat#repeats": 4, 
  "##characteristics#run#return_code#all": [
    0, 
    0, 
    0, 
    0
  ], 
  "##characteristics#run#return_code#all_unique": [
    0
  ], 
  "##characteristics#run#return_code#center": 0, 
  "##characteristics#run#return_code#exp": 0.0, 
  "##characteristics#run#return_code#exp_allx": [
    0.0
  ], 
  "##characteristics#run#return_code#exp_ally": [
    100.0
  ], 
  "##characteristics#run#return_code#exp_warning": "no", 
  "##characteristics#run#return_code#halfrange": 0, 
  "##characteristics#run#return_code#max": 0, 
  "##characteristics#run#return_code#mean": 0.0, 
  "##characteristics#run#return_code#min": 0, 
  "##characteristics#run#return_code#range": 0, 
  "##characteristics#run#return_code#repeats": 4, 
  "##characteristics#run#run_success#all": [
    "yes", 
    "yes", 
    "yes", 
    "yes"
  ], 
  "##characteristics#run#run_success#all_unique": [
    "yes"
  ], 
  "##characteristics#run#run_success#min": "yes", 
  "##characteristics#run#run_success#repeats": 4, 
  "##characteristics#run#run_success_bool#all": [
    true, 
    true, 
    true, 
    true
  ], 
  "##characteristics#run#run_success_bool#all_unique": [
    true
  ], 
  "##characteristics#run#run_success_bool#min": true, 
  "##characteristics#run#run_success_bool#repeats": 4, 
  "##characteristics#run#total_execution_time#all": [
    9.202963, 
    9.191364, 
    9.17342, 
    9.182481
  ], 
  "##characteristics#run#total_execution_time#all_unique": [
    9.202963, 
    9.191364, 
    9.17342, 
    9.182481
  ], 
  "##characteristics#run#total_execution_time#center": 9.1881915, 
  "##characteristics#run#total_execution_time#exp": 9.185058151515152, 
  "##characteristics#run#total_execution_time#exp_allx": [
    9.185058151515152
  ], 
  "##characteristics#run#total_execution_time#exp_ally": [
    0.1121448157755102
  ], 
  "##characteristics#run#total_execution_time#exp_warning": "no", 
  "##characteristics#run#total_execution_time#halfrange": 0.01477150000000016, 
  "##characteristics#run#total_execution_time#max": 9.202963, 
  "##characteristics#run#total_execution_time#mean": 9.187557, 
  "##characteristics#run#total_execution_time#min": 9.17342, 
  "##characteristics#run#total_execution_time#range": 0.02954300000000032, 
  "##characteristics#run#total_execution_time#range_percent": 0.003220500097019467, 
  "##characteristics#run#total_execution_time#repeats": 4
}
