{
  "##characteristics#compile#binary_size#all": [
    9752
  ], 
  "##characteristics#compile#binary_size#all_unique": [
    9752
  ], 
  "##characteristics#compile#binary_size#center": 9752, 
  "##characteristics#compile#binary_size#center_imp": 0.9983593109105825, 
  "##characteristics#compile#binary_size#exp": 9752.0, 
  "##characteristics#compile#binary_size#exp_allx": [
    9752.0
  ], 
  "##characteristics#compile#binary_size#exp_ally": [
    100.0
  ], 
  "##characteristics#compile#binary_size#exp_imp": 0.9983593109105825, 
  "##characteristics#compile#binary_size#exp_warning": "no", 
  "##characteristics#compile#binary_size#halfrange": 0, 
  "##characteristics#compile#binary_size#max": 9752, 
  "##characteristics#compile#binary_size#mean": 9752.0, 
  "##characteristics#compile#binary_size#mean_imp": 0.9983593109105825, 
  "##characteristics#compile#binary_size#min": 9752, 
  "##characteristics#compile#binary_size#min_imp": 0.9983593109105825, 
  "##characteristics#compile#binary_size#range": 0, 
  "##characteristics#compile#binary_size#range_percent": 0, 
  "##characteristics#compile#binary_size#repeats": 1, 
  "##characteristics#compile#compilation_success#all": [
    "yes"
  ], 
  "##characteristics#compile#compilation_success#all_unique": [
    "yes"
  ], 
  "##characteristics#compile#compilation_success#min": "yes", 
  "##characteristics#compile#compilation_success#min_imp": 0, 
  "##characteristics#compile#compilation_success#repeats": 1, 
  "##characteristics#compile#compilation_success_bool#all": [
    true
  ], 
  "##characteristics#compile#compilation_success_bool#all_unique": [
    true
  ], 
  "##characteristics#compile#compilation_success_bool#min": true, 
  "##characteristics#compile#compilation_success_bool#min_imp": 0, 
  "##characteristics#compile#compilation_success_bool#repeats": 1, 
  "##characteristics#compile#compilation_time#all": [
    0.1632699966430664
  ], 
  "##characteristics#compile#compilation_time#all_unique": [
    0.1632699966430664
  ], 
  "##characteristics#compile#compilation_time#center": 0.1632699966430664, 
  "##characteristics#compile#compilation_time#center_imp": 0.9867334302953837, 
  "##characteristics#compile#compilation_time#exp": 0.1632699966430664, 
  "##characteristics#compile#compilation_time#exp_allx": [
    0.1632699966430664
  ], 
  "##characteristics#compile#compilation_time#exp_ally": [
    100.0
  ], 
  "##characteristics#compile#compilation_time#exp_imp": 0.9867334302953837, 
  "##characteristics#compile#compilation_time#exp_warning": "no", 
  "##characteristics#compile#compilation_time#halfrange": 0.0, 
  "##characteristics#compile#compilation_time#max": 0.1632699966430664, 
  "##characteristics#compile#compilation_time#mean": 0.1632699966430664, 
  "##characteristics#compile#compilation_time#mean_imp": 0.9867334302953837, 
  "##characteristics#compile#compilation_time#min": 0.1632699966430664, 
  "##characteristics#compile#compilation_time#min_imp": 0.9867334302953837, 
  "##characteristics#compile#compilation_time#range": 0.0, 
  "##characteristics#compile#compilation_time#range_percent": 0.0, 
  "##characteristics#compile#compilation_time#repeats": 1, 
  "##characteristics#compile#compilation_time_with_module#all": [
    1.5964350700378418
  ], 
  "##characteristics#compile#compilation_time_with_module#all_unique": [
    1.5964350700378418
  ], 
  "##characteristics#compile#compilation_time_with_module#center": 1.5964350700378418, 
  "##characteristics#compile#compilation_time_with_module#center_imp": 0.9886903007108493, 
  "##characteristics#compile#compilation_time_with_module#exp": 1.5964350700378418, 
  "##characteristics#compile#compilation_time_with_module#exp_allx": [
    1.5964350700378418
  ], 
  "##characteristics#compile#compilation_time_with_module#exp_ally": [
    100.0
  ], 
  "##characteristics#compile#compilation_time_with_module#exp_imp": 0.9886903007108493, 
  "##characteristics#compile#compilation_time_with_module#exp_warning": "no", 
  "##characteristics#compile#compilation_time_with_module#halfrange": 0.0, 
  "##characteristics#compile#compilation_time_with_module#max": 1.5964350700378418, 
  "##characteristics#compile#compilation_time_with_module#mean": 1.5964350700378418, 
  "##characteristics#compile#compilation_time_with_module#mean_imp": 0.9886903007108493, 
  "##characteristics#compile#compilation_time_with_module#min": 1.5964350700378418, 
  "##characteristics#compile#compilation_time_with_module#min_imp": 0.9886903007108493, 
  "##characteristics#compile#compilation_time_with_module#range": 0.0, 
  "##characteristics#compile#compilation_time_with_module#range_percent": 0.0, 
  "##characteristics#compile#compilation_time_with_module#repeats": 1, 
  "##characteristics#compile#joined_compiler_flags#all": [
    "-O3 -fschedule-insns"
  ], 
  "##characteristics#compile#joined_compiler_flags#all_unique": [
    "-O3 -fschedule-insns"
  ], 
  "##characteristics#compile#joined_compiler_flags#min": "-O3 -fschedule-insns", 
  "##characteristics#compile#joined_compiler_flags#min_imp": 0, 
  "##characteristics#compile#joined_compiler_flags#repeats": 1, 
  "##characteristics#compile#md5_sum#all": [
    "b9f7c84f4a2e8c71c036f9714dba99c5"
  ], 
  "##characteristics#compile#md5_sum#all_unique": [
    "b9f7c84f4a2e8c71c036f9714dba99c5"
  ], 
  "##characteristics#compile#md5_sum#min": "b9f7c84f4a2e8c71c036f9714dba99c5", 
  "##characteristics#compile#md5_sum#min_imp": 0, 
  "##characteristics#compile#md5_sum#repeats": 1, 
  "##characteristics#compile#obj_size#all": [
    5664
  ], 
  "##characteristics#compile#obj_size#all_unique": [
    5664
  ], 
  "##characteristics#compile#obj_size#center": 5664, 
  "##characteristics#compile#obj_size#center_imp": 0.9915254237288136, 
  "##characteristics#compile#obj_size#exp": 5664.0, 
  "##characteristics#compile#obj_size#exp_allx": [
    5664.0
  ], 
  "##characteristics#compile#obj_size#exp_ally": [
    100.0
  ], 
  "##characteristics#compile#obj_size#exp_imp": 0.9915254237288136, 
  "##characteristics#compile#obj_size#exp_warning": "no", 
  "##characteristics#compile#obj_size#halfrange": 0, 
  "##characteristics#compile#obj_size#max": 5664, 
  "##characteristics#compile#obj_size#mean": 5664.0, 
  "##characteristics#compile#obj_size#mean_imp": 0.9915254237288136, 
  "##characteristics#compile#obj_size#min": 5664, 
  "##characteristics#compile#obj_size#min_imp": 0.9915254237288136, 
  "##characteristics#compile#obj_size#range": 0, 
  "##characteristics#compile#obj_size#range_percent": 0, 
  "##characteristics#compile#obj_size#repeats": 1, 
  "##characteristics#compile#obj_sizes#fft.codelet__2.o#all": [
    2528
  ], 
  "##characteristics#compile#obj_sizes#fft.codelet__2.o#all_unique": [
    2528
  ], 
  "##characteristics#compile#obj_sizes#fft.codelet__2.o#center": 2528, 
  "##characteristics#compile#obj_sizes#fft.codelet__2.o#center_imp": 0.9810126582278481, 
  "##characteristics#compile#obj_sizes#fft.codelet__2.o#exp": 2528.0, 
  "##characteristics#compile#obj_sizes#fft.codelet__2.o#exp_allx": [
    2528.0
  ], 
  "##characteristics#compile#obj_sizes#fft.codelet__2.o#exp_ally": [
    100.0
  ], 
  "##characteristics#compile#obj_sizes#fft.codelet__2.o#exp_imp": 0.9810126582278481, 
  "##characteristics#compile#obj_sizes#fft.codelet__2.o#exp_warning": "no", 
  "##characteristics#compile#obj_sizes#fft.codelet__2.o#halfrange": 0, 
  "##characteristics#compile#obj_sizes#fft.codelet__2.o#max": 2528, 
  "##characteristics#compile#obj_sizes#fft.codelet__2.o#mean": 2528.0, 
  "##characteristics#compile#obj_sizes#fft.codelet__2.o#mean_imp": 0.9810126582278481, 
  "##characteristics#compile#obj_sizes#fft.codelet__2.o#min": 2528, 
  "##characteristics#compile#obj_sizes#fft.codelet__2.o#min_imp": 0.9810126582278481, 
  "##characteristics#compile#obj_sizes#fft.codelet__2.o#range": 0, 
  "##characteristics#compile#obj_sizes#fft.codelet__2.o#range_percent": 0, 
  "##characteristics#compile#obj_sizes#fft.codelet__2.o#repeats": 1, 
  "##characteristics#compile#obj_sizes#fft.codelet__2.wrapper.o#all": [
    3136
  ], 
  "##characteristics#compile#obj_sizes#fft.codelet__2.wrapper.o#all_unique": [
    3136
  ], 
  "##characteristics#compile#obj_sizes#fft.codelet__2.wrapper.o#center": 3136, 
  "##characteristics#compile#obj_sizes#fft.codelet__2.wrapper.o#center_imp": 1.0, 
  "##characteristics#compile#obj_sizes#fft.codelet__2.wrapper.o#exp": 3136.0, 
  "##characteristics#compile#obj_sizes#fft.codelet__2.wrapper.o#exp_allx": [
    3136.0
  ], 
  "##characteristics#compile#obj_sizes#fft.codelet__2.wrapper.o#exp_ally": [
    100.0
  ], 
  "##characteristics#compile#obj_sizes#fft.codelet__2.wrapper.o#exp_imp": 1.0, 
  "##characteristics#compile#obj_sizes#fft.codelet__2.wrapper.o#exp_warning": "no", 
  "##characteristics#compile#obj_sizes#fft.codelet__2.wrapper.o#halfrange": 0, 
  "##characteristics#compile#obj_sizes#fft.codelet__2.wrapper.o#max": 3136, 
  "##characteristics#compile#obj_sizes#fft.codelet__2.wrapper.o#mean": 3136.0, 
  "##characteristics#compile#obj_sizes#fft.codelet__2.wrapper.o#mean_imp": 1.0, 
  "##characteristics#compile#obj_sizes#fft.codelet__2.wrapper.o#min": 3136, 
  "##characteristics#compile#obj_sizes#fft.codelet__2.wrapper.o#min_imp": 1.0, 
  "##characteristics#compile#obj_sizes#fft.codelet__2.wrapper.o#range": 0, 
  "##characteristics#compile#obj_sizes#fft.codelet__2.wrapper.o#range_percent": 0, 
  "##characteristics#compile#obj_sizes#fft.codelet__2.wrapper.o#repeats": 1, 
  "##characteristics#compile#program_git_hash#all": [
    "ebb128a094a9981cc32d00b103628cee925ff171"
  ], 
  "##characteristics#compile#program_git_hash#all_unique": [
    "ebb128a094a9981cc32d00b103628cee925ff171"
  ], 
  "##characteristics#compile#program_git_hash#min": "ebb128a094a9981cc32d00b103628cee925ff171", 
  "##characteristics#compile#program_git_hash#min_imp": 0, 
  "##characteristics#compile#program_git_hash#repeats": 1, 
  "##characteristics#run#execution_time#all": [
    1.6477068871018126e-05, 
    1.6478204343979092e-05
  ], 
  "##characteristics#run#execution_time#all_unique": [
    1.6477068871018126e-05, 
    1.6478204343979092e-05
  ], 
  "##characteristics#run#execution_time#center": 1.6477636607498608e-05, 
  "##characteristics#run#execution_time#center_imp": 1.1348673685149802, 
  "##characteristics#run#execution_time#exp": 1.6477068871018126e-05, 
  "##characteristics#run#execution_time#exp_allx": [
    1.6477068871018126e-05
  ], 
  "##characteristics#run#execution_time#exp_ally": [
    42038.904113176395
  ], 
  "##characteristics#run#execution_time#exp_imp": 1.1349019305098207, 
  "##characteristics#run#execution_time#exp_warning": "no", 
  "##characteristics#run#execution_time#halfrange": 5.677364804831491e-10, 
  "##characteristics#run#execution_time#max": 1.6478204343979092e-05, 
  "##characteristics#run#execution_time#mean": 1.6477636607498608e-05, 
  "##characteristics#run#execution_time#mean_imp": 1.1348673685149802, 
  "##characteristics#run#execution_time#min": 1.6477068871018126e-05, 
  "##characteristics#run#execution_time#min_imp": 1.1349019305098207, 
  "##characteristics#run#execution_time#range": 1.1354729609662983e-09, 
  "##characteristics#run#execution_time#range_percent": 6.891231503944894e-05, 
  "##characteristics#run#execution_time#repeats": 2, 
  "##characteristics#run#execution_time_kernel_0#all": [
    8.808295, 
    8.808902
  ], 
  "##characteristics#run#execution_time_kernel_0#all_unique": [
    8.808295, 
    8.808902
  ], 
  "##characteristics#run#execution_time_kernel_0#center": 8.808598499999999, 
  "##characteristics#run#execution_time_kernel_0#center_imp": 1.1348673685149802, 
  "##characteristics#run#execution_time_kernel_0#exp": 8.808295, 
  "##characteristics#run#execution_time_kernel_0#exp_allx": [
    8.808295
  ], 
  "##characteristics#run#execution_time_kernel_0#exp_ally": [
    0.07863927335936578
  ], 
  "##characteristics#run#execution_time_kernel_0#exp_imp": 1.1349019305098207, 
  "##characteristics#run#execution_time_kernel_0#exp_warning": "no", 
  "##characteristics#run#execution_time_kernel_0#halfrange": 0.00030350000000023414, 
  "##characteristics#run#execution_time_kernel_0#max": 8.808902, 
  "##characteristics#run#execution_time_kernel_0#mean": 8.808598499999999, 
  "##characteristics#run#execution_time_kernel_0#mean_imp": 1.1348673685149802, 
  "##characteristics#run#execution_time_kernel_0#min": 8.808295, 
  "##characteristics#run#execution_time_kernel_0#min_imp": 1.1349019305098207, 
  "##characteristics#run#execution_time_kernel_0#range": 0.0006070000000004683, 
  "##characteristics#run#execution_time_kernel_0#range_percent": 6.891231503945636e-05, 
  "##characteristics#run#execution_time_kernel_0#repeats": 2, 
  "##characteristics#run#execution_time_with_module#all": [
    9.321680068969727, 
    9.323853015899658
  ], 
  "##characteristics#run#execution_time_with_module#all_unique": [
    9.321680068969727, 
    9.323853015899658
  ], 
  "##characteristics#run#execution_time_with_module#center": 9.322766542434692, 
  "##characteristics#run#execution_time_with_module#center_imp": 1.1275046949023768, 
  "##characteristics#run#execution_time_with_module#exp": 9.321680068969727, 
  "##characteristics#run#execution_time_with_module#exp_allx": [
    9.321680068969727
  ], 
  "##characteristics#run#execution_time_with_module#exp_ally": [
    0.07430233929252499
  ], 
  "##characteristics#run#execution_time_with_module#exp_imp": 1.1274789528660831, 
  "##characteristics#run#execution_time_with_module#exp_warning": "no", 
  "##characteristics#run#execution_time_with_module#halfrange": 0.0010864734649658203, 
  "##characteristics#run#execution_time_with_module#max": 9.323853015899658, 
  "##characteristics#run#execution_time_with_module#mean": 9.322766542434692, 
  "##characteristics#run#execution_time_with_module#mean_imp": 1.1275046949023768, 
  "##characteristics#run#execution_time_with_module#min": 9.321680068969727, 
  "##characteristics#run#execution_time_with_module#min_imp": 1.1274789528660831, 
  "##characteristics#run#execution_time_with_module#range": 0.0021729469299316406, 
  "##characteristics#run#execution_time_with_module#range_percent": 0.00023310679124946673, 
  "##characteristics#run#execution_time_with_module#repeats": 2, 
  "##characteristics#run#repeat#all": [
    534579, 
    534579
  ], 
  "##characteristics#run#repeat#all_unique": [
    534579
  ], 
  "##characteristics#run#repeat#center": 534579, 
  "##characteristics#run#repeat#center_imp": 1.0, 
  "##characteristics#run#repeat#exp": 534579.0, 
  "##characteristics#run#repeat#exp_allx": [
    534579.0
  ], 
  "##characteristics#run#repeat#exp_ally": [
    100.0
  ], 
  "##characteristics#run#repeat#exp_imp": 1.0, 
  "##characteristics#run#repeat#exp_warning": "no", 
  "##characteristics#run#repeat#halfrange": 0, 
  "##characteristics#run#repeat#max": 534579, 
  "##characteristics#run#repeat#mean": 534579.0, 
  "##characteristics#run#repeat#mean_imp": 1.0, 
  "##characteristics#run#repeat#min": 534579, 
  "##characteristics#run#repeat#min_imp": 1.0, 
  "##characteristics#run#repeat#range": 0, 
  "##characteristics#run#repeat#range_percent": 0, 
  "##characteristics#run#repeat#repeats": 2, 
  "##characteristics#run#return_code#all": [
    0, 
    0
  ], 
  "##characteristics#run#return_code#all_unique": [
    0
  ], 
  "##characteristics#run#return_code#center": 0, 
  "##characteristics#run#return_code#exp": 0.0, 
  "##characteristics#run#return_code#exp_allx": [
    0.0
  ], 
  "##characteristics#run#return_code#exp_ally": [
    100.0
  ], 
  "##characteristics#run#return_code#exp_warning": "no", 
  "##characteristics#run#return_code#halfrange": 0, 
  "##characteristics#run#return_code#max": 0, 
  "##characteristics#run#return_code#mean": 0.0, 
  "##characteristics#run#return_code#min": 0, 
  "##characteristics#run#return_code#range": 0, 
  "##characteristics#run#return_code#repeats": 2, 
  "##characteristics#run#run_success#all": [
    "yes", 
    "yes"
  ], 
  "##characteristics#run#run_success#all_unique": [
    "yes"
  ], 
  "##characteristics#run#run_success#min": "yes", 
  "##characteristics#run#run_success#min_imp": 1, 
  "##characteristics#run#run_success#repeats": 2, 
  "##characteristics#run#run_success_bool#all": [
    true, 
    true
  ], 
  "##characteristics#run#run_success_bool#all_unique": [
    true
  ], 
  "##characteristics#run#run_success_bool#min": true, 
  "##characteristics#run#run_success_bool#min_imp": 1, 
  "##characteristics#run#run_success_bool#repeats": 2, 
  "##characteristics#run#total_execution_time#all": [
    8.808295, 
    8.808902
  ], 
  "##characteristics#run#total_execution_time#all_unique": [
    8.808295, 
    8.808902
  ], 
  "##characteristics#run#total_execution_time#center": 8.808598499999999, 
  "##characteristics#run#total_execution_time#center_imp": 1.1348673685149802, 
  "##characteristics#run#total_execution_time#exp": 8.808295, 
  "##characteristics#run#total_execution_time#exp_allx": [
    8.808295
  ], 
  "##characteristics#run#total_execution_time#exp_ally": [
    0.07863927335936578
  ], 
  "##characteristics#run#total_execution_time#exp_imp": 1.1349019305098207, 
  "##characteristics#run#total_execution_time#exp_warning": "no", 
  "##characteristics#run#total_execution_time#halfrange": 0.00030350000000023414, 
  "##characteristics#run#total_execution_time#max": 8.808902, 
  "##characteristics#run#total_execution_time#mean": 8.808598499999999, 
  "##characteristics#run#total_execution_time#mean_imp": 1.1348673685149802, 
  "##characteristics#run#total_execution_time#min": 8.808295, 
  "##characteristics#run#total_execution_time#min_imp": 1.1349019305098207, 
  "##characteristics#run#total_execution_time#range": 0.0006070000000004683, 
  "##characteristics#run#total_execution_time#range_percent": 6.891231503945636e-05, 
  "##characteristics#run#total_execution_time#repeats": 2
}
